diyaps_toolbox.py
diyaps_toolbox-0.0.2.dist-info/LICENSE.txt
diyaps_toolbox-0.0.2.dist-info/METADATA
diyaps_toolbox-0.0.2.dist-info/WHEEL
diyaps_toolbox-0.0.2.dist-info/top_level.txt
diyaps_toolbox-0.0.2.dist-info/RECORD
