Metadata-Version: 2.1
Name: diyaps_toolbox
Version: 0.0.2
Summary: Package for working with DIYAPs files
Home-page: UNKNOWN
Author: Wiktoria Staszak
License: UNKNOWN
Platform: UNKNOWN
Classifier: Programming Language :: Python :: 3
Classifier: License :: OSI Approved :: MIT License
Classifier: Operating System :: OS Independent
Requires-Python: >=3.6
License-File: LICENSE.txt
